Topsis_Bandhan_102003440/Bandhan_102003440.py
Topsis_Bandhan_102003440-1.3.dist-info/License.txt
Topsis_Bandhan_102003440-1.3.dist-info/METADATA
Topsis_Bandhan_102003440-1.3.dist-info/WHEEL
Topsis_Bandhan_102003440-1.3.dist-info/entry_points.txt
Topsis_Bandhan_102003440-1.3.dist-info/top_level.txt
Topsis_Bandhan_102003440-1.3.dist-info/RECORD
