Metadata-Version: 2.1
Name: Topsis-Bandhan-102003440
Version: 1.3
Summary: Doing Evaluation of alternatives based on multiple criteria using TOPSIS method.
Author: Bandhan Sher Singh
Author-email: bsingh3_be20@thapar.edu
Classifier: Programming Language :: Python :: 3
Classifier: License :: OSI Approved :: MIT License
Classifier: Operating System :: OS Independent
License-File: License.txt
Requires-Dist: pandas
